Metadata-Version: 2.1
Name: import-java
Version: 0.6
Summary: Import Java packages seamlessly into CPython
Home-page: https://github.com/Arnie97/import-java
Author: Arnie97
Author-email: Arnie97@gmail.com
License: MIT
Platform: UNKNOWN
Classifier: Development Status :: 4 - Beta
Classifier: Intended Audience :: Developers
Classifier: Topic :: Software Development :: Libraries :: Java Libraries
Classifier: License :: OSI Approved :: MIT License
Classifier: Programming Language :: Python :: 3
Classifier: Programming Language :: Python :: 3 :: Only
Classifier: Programming Language :: Java
Requires-Python: >=3.0
